[
  {
    "model": "SGBM",
    "setting": "default",
    "raw_depth_mae_mm": 19.899514263206058,
    "raw_depth_rmse_mm": 104.6342283434338,
    "valid_disp_depth_mae_mm": 19.899514263206058,
    "valid_disp_depth_rmse_mm": 104.6342283434338,
    "depth_mae_cap100_mm": 5.480814939075046,
    "depth_rmse_cap100_mm": 9.733467615975274,
    "depth_mae_cap200_mm": 6.729956301053365,
    "depth_rmse_cap200_mm": 14.155562408765157,
    "depth_median_abs_error_mm": 2.9895980834960936,
    "depth_abs_error_p95_mm": 77.86420962015788,
    "depth_abs_error_p99_mm": 373.86693714194826,
    "bad_1mm": 49.84191128966059,
    "bad_2mm": 32.44508934002949,
    "bad_5mm": 17.83735806932027,
    "pred_disp_le_0_1_ratio": 0.3967665527157156,
    "pred_disp_le_0_5_ratio": 0.3967665527157156,
    "runtime_ms_mean": 68.81529875099659,
    "notes": "OpenCV SGBM max_disp=320 block=3; raw mask keeps historical pred>0 filter"
  },
  {
    "model": "S2M2-L",
    "setting": "resize1024",
    "raw_depth_mae_mm": 3.3912790252102747,
    "raw_depth_rmse_mm": 9.830771912468805,
    "valid_disp_depth_mae_mm": 3.3912790252102747,
    "valid_disp_depth_rmse_mm": 9.830771912468805,
    "depth_mae_cap100_mm": 4.360008996725083,
    "depth_rmse_cap100_mm": 11.433819193310208,
    "depth_mae_cap200_mm": 3.3912790252102747,
    "depth_rmse_cap200_mm": 9.830771912468805,
    "depth_median_abs_error_mm": 2.8610014809502498,
    "depth_abs_error_p95_mm": 7.6168928954336375,
    "depth_abs_error_p99_mm": 11.524710249900817,
    "bad_1mm": 43.534848764565844,
    "bad_2mm": 25.943082351713798,
    "bad_5mm": 14.83918076838849,
    "pred_disp_le_0_1_ratio": 0.0,
    "pred_disp_le_0_5_ratio": 0.0,
    "runtime_ms_mean": 143.666250920958,
    "notes": "S2M2-L, max_width=1024"
  },
  {
    "model": "S2M2-L",
    "setting": "full-res",
    "raw_depth_mae_mm": 3.661766960223516,
    "raw_depth_rmse_mm": 10.047787029213376,
    "valid_disp_depth_mae_mm": 3.661766960223516,
    "valid_disp_depth_rmse_mm": 10.047787029213376,
    "depth_mae_cap100_mm": 4.634136778116226,
    "depth_rmse_cap100_mm": 11.650203997559018,
    "depth_mae_cap200_mm": 3.661766960223516,
    "depth_rmse_cap200_mm": 10.047787029213376,
    "depth_median_abs_error_mm": 3.2511223051283094,
    "depth_abs_error_p95_mm": 7.95418141550488,
    "depth_abs_error_p99_mm": 11.870173422495524,
    "bad_1mm": 44.389788549992154,
    "bad_2mm": 27.283527291501407,
    "bad_5mm": 17.029972767939842,
    "pred_disp_le_0_1_ratio": 0.0,
    "pred_disp_le_0_5_ratio": 0.0,
    "runtime_ms_mean": 217.09916649593248,
    "notes": "S2M2-L, original 1024x1280"
  },
  {
    "model": "S2M2-XL",
    "setting": "resize1024",
    "raw_depth_mae_mm": 2.2148483554522196,
    "raw_depth_rmse_mm": 8.613050893942516,
    "valid_disp_depth_mae_mm": 2.2148483554522196,
    "valid_disp_depth_rmse_mm": 8.613050893942516,
    "depth_mae_cap100_mm": 3.1933846791585285,
    "depth_rmse_cap100_mm": 10.22868254184723,
    "depth_mae_cap200_mm": 2.2148483554522196,
    "depth_rmse_cap200_mm": 8.613050893942516,
    "depth_median_abs_error_mm": 1.7335487577650281,
    "depth_abs_error_p95_mm": 5.729392304685381,
    "depth_abs_error_p99_mm": 9.822956207063463,
    "bad_1mm": 40.94283873368931,
    "bad_2mm": 22.66759327322286,
    "bad_5mm": 11.261898412424493,
    "pred_disp_le_0_1_ratio": 0.0,
    "pred_disp_le_0_5_ratio": 0.0,
    "runtime_ms_mean": 246.38646476798587,
    "notes": "S2M2-XL, max_width=1024"
  },
  {
    "model": "S2M2-XL",
    "setting": "full-res",
    "raw_depth_mae_mm": 2.719322669506073,
    "raw_depth_rmse_mm": 9.079755294322968,
    "valid_disp_depth_mae_mm": 2.719322669506073,
    "valid_disp_depth_rmse_mm": 9.079755294322968,
    "depth_mae_cap100_mm": 3.7020128846168516,
    "depth_rmse_cap100_mm": 10.697831128703223,
    "depth_mae_cap200_mm": 2.719322669506073,
    "depth_rmse_cap200_mm": 9.079755294322968,
    "depth_median_abs_error_mm": 2.2971646626790365,
    "depth_abs_error_p95_mm": 6.170662367343903,
    "depth_abs_error_p99_mm": 10.186873314115736,
    "bad_1mm": 42.411380177275305,
    "bad_2mm": 24.665539171346825,
    "bad_5mm": 13.838865063602665,
    "pred_disp_le_0_1_ratio": 0.0,
    "pred_disp_le_0_5_ratio": 0.0,
    "runtime_ms_mean": 385.39958679013785,
    "notes": "S2M2-XL, original 1024x1280"
  },
  {
    "model": "Fast-FoundationStereo",
    "setting": "ONNX 320x736",
    "raw_depth_mae_mm": 5093.623824067248,
    "raw_depth_rmse_mm": 760149.9261218297,
    "valid_disp_depth_mae_mm": 2.5958792057302262,
    "valid_disp_depth_rmse_mm": 11.363538414902157,
    "depth_mae_cap100_mm": 3.498164666361279,
    "depth_rmse_cap100_mm": 10.800684950086806,
    "depth_mae_cap200_mm": 2.5672206355465783,
    "depth_rmse_cap200_mm": 9.382276080714332,
    "depth_median_abs_error_mm": 1.7865305794609918,
    "depth_abs_error_p95_mm": 7.207157193289863,
    "depth_abs_error_p99_mm": 12.932623481750488,
    "bad_1mm": 40.107144268628325,
    "bad_2mm": 23.28385468735774,
    "bad_5mm": 12.689869386257898,
    "pred_disp_le_0_1_ratio": 1.030031053774931e-06,
    "pred_disp_le_0_5_ratio": 1.5616599847555402e-06,
    "runtime_ms_mean": 43.28093168636163,
    "notes": "20_30_48 iters=4 ONNX; fixed 320x736 input, disparity rescaled to GT resolution"
  }
]